listener/agent.py
volttron-listener-default-vip-id
volttron_listener-2.0.0rc3.dist-info/LICENSE
volttron_listener-2.0.0rc3.dist-info/METADATA
volttron_listener-2.0.0rc3.dist-info/WHEEL
volttron_listener-2.0.0rc3.dist-info/entry_points.txt
volttron_listener-2.0.0rc3.dist-info/RECORD
