Metadata-Version: 2.3
Name: volttron-listener
Version: 2.0.0rc3
Summary: The volttron-listener agent allows publishing of message bus traffic to standard out.
License: Apache-2.0
Author: VOLTTRON Team
Author-email: volttron@pnnl.gov
Requires-Python: >=3.10,<4.0
Classifier: Intended Audience :: Developers
Classifier: Intended Audience :: Information Technology
Classifier: Intended Audience :: Other Audience
Classifier: Intended Audience :: Science/Research
Classifier: License :: OSI Approved :: Apache Software License
Classifier: Programming Language :: Python :: 3
Classifier: Programming Language :: Python :: 3.10
Classifier: Programming Language :: Python :: 3.11
Classifier: Programming Language :: Python :: 3.12
Classifier: Programming Language :: Python :: 3.13
Classifier: Programming Language :: Python :: 3 :: Only
Requires-Dist: volttron-core (>=2.0.0rc13)
Project-URL: Homepage, https://github.com/eclipse-volttron/volttron-listener
Project-URL: Repository, https://github.com/eclipse-volttron/volttron-listener
